{
  "brand": "AC Infinity",
  "series": "CLOUDLINE A-Series (LITE/value)",
  "model": "CLOUDLINE A8",
  "status": "active",
  "fan_role": "both",
  "fan_type": "inline_mixed_flow",
  "motor_type": "EC",
  "flange_diameter_mm": 200,
  "max_airflow_m3_h": 1230.1,
  "recommended_airflow_m3_h": null,
  "static_pressure_pa": 746,
  "noise_db_min": null,
  "noise_db_max": 42,
  "power_watts_min": 72,
  "power_watts_max": 190,
  "speed_control_type": "external_stepless_controller",
  "controller_included": true,
  "app_control": false,
  "wifi": false,
  "bluetooth": false,
  "length_mm": 310,
  "diameter_mm": null,
  "weight_kg": null,
  "source_url": "https://acinfinity.com/cloudline-a8-quiet-inline-fan-8-with-speed-controller/",
  "source_type": "manufacturer",
  "source_date": "2026-06-27",
  "confidence_level": "A",
  "uvp_amount": 159,
  "uvp_currency": "EUR",
  "notes": "acinfinity.com: 724CFM=1230m3/h, 746Pa, 42dBA, 190W max/72W avg, 2.8A. ASIN confirmed amazon.com Lite A8; amazon.de listing not directly verified. UVP acinfinity.eu."
}