{
  "brand": "CarbonActive",
  "series": "CarbonActive EC fan (EC Power Box)",
  "model": "EC Power Box 750 m³/h",
  "status": "active",
  "fan_role": "both",
  "fan_type": "inline_centrifugal",
  "motor_type": "EC",
  "flange_diameter_mm": 200,
  "max_airflow_m3_h": 750,
  "recommended_airflow_m3_h": null,
  "static_pressure_pa": 700,
  "noise_db_min": null,
  "noise_db_max": null,
  "power_watts_min": null,
  "power_watts_max": 85,
  "speed_control_type": "external_stepless_controller",
  "controller_included": false,
  "app_control": false,
  "wifi": false,
  "bluetooth": false,
  "length_mm": null,
  "diameter_mm": null,
  "weight_kg": 7.2,
  "source_url": "https://holos.ch/de/carbonactive-ec-powerbox-750m3.html",
  "source_type": "retailer",
  "source_date": "2026-06-27",
  "confidence_level": "B",
  "uvp_amount": null,
  "uvp_currency": null,
  "notes": "Flange 200mm (not 160). 700Pa max (some list 610Pa w/filter), 83-85W/0.8A, 7.2kg. holos.ch / growandstyle.de"
}