{
  "brand": "GSE",
  "series": "Mini Grower",
  "model": "Mini Grower",
  "revision": null,
  "status": "active",
  "controller_type": "multi_function_controller",
  "controller_role": "primary",
  "system_category": "standalone",
  "supported_devices": "HID grow lights (up to 9×600W at 380V / 4×600W at 230V), AC fans (intake/exhaust), irrigation pumps",
  "max_device_count": null,
  "max_ports": null,
  "port_types": "Schuko outlet (multiple), CEE16 3-pole 16A input",
  "plug_type": "EU",
  "output_voltage_v": 230,
  "max_load_watts": null,
  "max_load_amps": 16,
  "sensor_temperature": true,
  "sensor_humidity": false,
  "sensor_vpd": false,
  "sensor_co2": false,
  "sensor_light": false,
  "sensor_soil_moisture": false,
  "sensor_water_temp": false,
  "sensor_ph": false,
  "sensor_ec": false,
  "sensor_level": false,
  "sensor_pressure": true,
  "control_temperature": true,
  "control_humidity": false,
  "control_vpd": false,
  "control_fan_speed": true,
  "control_light_schedule": true,
  "control_light_dimming": false,
  "control_ir_uv": false,
  "control_co2": false,
  "control_irrigation": true,
  "control_ph": false,
  "control_ec": false,
  "control_heater": false,
  "control_dehumidifier": false,
  "control_humidifier": false,
  "control_pump": true,
  "app_control": false,
  "wifi": false,
  "bluetooth": false,
  "cloud_required": false,
  "local_control": true,
  "api_available": false,
  "mqtt_available": false,
  "automation_rules": true,
  "data_logging": false,
  "alerts": false,
  "display_included": true,
  "touchscreen": false,
  "firmware_updates": false,
  "ai_features": false,
  "ai_feature_type": "none",
  "ai_grow_assistant": false,
  "ai_climate_optimization": false,
  "ai_vpd_optimization": false,
  "ai_light_schedule_optimization": false,
  "ai_irrigation_optimization": false,
  "ai_nutrient_recommendations": false,
  "ai_anomaly_detection": false,
  "ai_alert_summarization": false,
  "ai_camera_analysis": false,
  "ai_plant_stage_detection": false,
  "ai_pest_detection": false,
  "ai_disease_detection": false,
  "ai_yield_prediction": false,
  "ai_training_recommendations": false,
  "ai_voice_assistant": false,
  "ai_requires_cloud": false,
  "ai_requires_subscription": false,
  "ai_data_export": false,
  "ai_notes": null,
  "compatible_ec_fans": null,
  "compatible_lights": "HID 600W ballast lights (up to 9 at 380V 3-phase, up to 4 at 230V single-phase)",
  "compatible_sensors": "temperature sensor (included with fan controller)",
  "compatible_humidifiers": null,
  "compatible_irrigation": "any 230V pump",
  "compatible_co2_equipment": null,
  "compatible_brand_ecosystem": "any",
  "supported_manufacturer_series": null,
  "power_supply_included": true,
  "mounting_type": "wall_mount",
  "length_mm": 430,
  "width_mm": 200,
  "height_mm": 95,
  "weight_kg": null,
  "recommended_tent_min_cm": null,
  "recommended_tent_max_cm": null,
  "recommended_use_note": "All-in-one hardwired panel for HID-based grow rooms; combines 24h light timer, temperature/negative-pressure fan controller, and pulse irrigation timer in one enclosure; requires 380V 3-phase for full 9-lamp capacity",
  "include_in_default_controller_calculator": true,
  "source_url": "https://www.1-hydroponics.co.uk/grow-lights/professional-controllers/mini-grower-complete-controller.html",
  "source_type": "retailer",
  "source_date": "2026-06-28",
  "confidence_level": "C",
  "uvp_amount": 389.9,
  "uvp_currency": "EUR",
  "uvp_source_url": "https://www.imagro.de/growbedarfartikel/gse-mini-grower_544.php",
  "uvp_source_type": "retailer",
  "uvp_source_date": "2026-06-28",
  "uvp_confidence_level": "C",
  "uvp_notes": "German retailer starting price; UK retailer (1-hydroponics.co.uk) lists at £440.95 GBP; price varies by configuration",
  "notes": "Hardwired all-in-one grow room control panel integrating: (1) 24h lighting timer with 36h power reserve for 9×600W HID lamps at 380V 3-phase (4 lamps at 230V), (2) digital temperature + negative-pressure fan controller, (3) second-pulse irrigation timer. Protection class IP44. Case dimensions 200×430×95mm. CEE16 3-phase input connector. Some German retailers show as out of stock; product may be legacy/limited production. Not sold on Amazon.de."
}